[
  {"externalId":"ikea-hr-bathroom-nysjoen-mirror-cabinet-white","name":"NYSJÖN Element s ogledalom, bijela, 50x60 cm","retailer":"IKEA","category":"storage","price":39.99,"productUrl":"https://www.ikea.com/hr/hr/p/nysjoen-element-s-ogledalom-bijela-10470830/","imageUrl":"https://www.ikea.com/hr/hr/images/products/nysjoen-element-s-ogledalom-bijela__0971578_pe811386_s5.jpg?f=xl","availabilityStatus":"in-stock","deliveryNote":"Provjeri dostavu ili preuzimanje prije kupnje.","lastCheckedAt":"2026-06-17","roomTags":["bathroom"],"styleTags":["modern","minimal"],"colorTags":["white"],"materialTags":["glass","metal"],"priceTier":"budget","reviewRating":4.2,"reviewCount":273,"market":"HR","sourceType":"public-product-page","sourceName":"IKEA HR","sourceReference":"hr-bathroom-10-17","dataQuality":"complete","dataQualityNotes":"Name + EUR price verified on the retailer site on 2026-06-16. Re-check before production.","imageVerified":true},
  {"externalId":"ikea-hr-bathroom-enhet-tall-frame-shelves-white","name":"ENHET Visoki okvir s policama, bijela, 30x30x180 cm","retailer":"IKEA","category":"storage","price":70,"productUrl":"https://www.ikea.com/hr/hr/p/enhet-visoki-okvir-s-policama-bijela-40448946/","imageUrl":"https://www.ikea.com/hr/hr/images/products/enhet-visoki-okvir-s-policama-bijela__0805440_pe769562_s5.jpg?f=xl","availabilityStatus":"in-stock","deliveryNote":"Provjeri dostavu ili preuzimanje prije kupnje.","lastCheckedAt":"2026-06-17","roomTags":["bathroom"],"styleTags":["modern","minimal"],"colorTags":["white"],"materialTags":["metal"],"priceTier":"budget","reviewRating":4.5,"reviewCount":211,"market":"HR","sourceType":"public-product-page","sourceName":"IKEA HR","sourceReference":"hr-bathroom-10-17","dataQuality":"complete","dataQualityNotes":"Name + EUR price verified on the retailer site on 2026-06-16. Re-check before production.","imageVerified":true},
  {"externalId":"ikea-hr-bathroom-taennforsen-mirror-cabinet-white","name":"TÄNNFORSEN Element s ogledalom i vratima, bijela, 100x15x95 cm","retailer":"IKEA","category":"storage","price":249,"productUrl":"https://www.ikea.com/hr/hr/p/taennforsen-element-s-ogledalom-i-vratima-bijela-00555250/","imageUrl":"https://www.ikea.com/hr/hr/images/products/taennforsen-element-s-ogledalom-i-vratima-bijela__1195283_pe902328_s5.jpg?f=xl","availabilityStatus":"in-stock","deliveryNote":"Provjeri dostavu ili preuzimanje prije kupnje.","lastCheckedAt":"2026-06-17","roomTags":["bathroom"],"styleTags":["modern","minimal"],"colorTags":["white"],"materialTags":["glass"],"priceTier":"standard","reviewRating":4.3,"reviewCount":66,"market":"HR","sourceType":"public-product-page","sourceName":"IKEA HR","sourceReference":"hr-bathroom-10-17","dataQuality":"complete","dataQualityNotes":"Name + EUR price verified on the retailer site on 2026-06-16. Re-check before production.","imageVerified":true},
  {"externalId":"ikea-hr-bathroom-vilto-shelf-birch","name":"VILTO Regal, breza, 46x150 cm","retailer":"IKEA","category":"storage","price":89.99,"productUrl":"https://www.ikea.com/hr/hr/p/vilto-regal-breza-90344456/","imageUrl":"https://www.ikea.com/hr/hr/images/products/vilto-regal-breza__0627212_pe693226_s5.jpg?f=xl","availabilityStatus":"in-stock","deliveryNote":"Provjeri dostavu ili preuzimanje prije kupnje.","lastCheckedAt":"2026-06-17","roomTags":["bathroom"],"styleTags":["minimal","cozy"],"colorTags":["natural"],"materialTags":["wood"],"priceTier":"budget","reviewRating":4.7,"reviewCount":425,"market":"HR","sourceType":"public-product-page","sourceName":"IKEA HR","sourceReference":"hr-bathroom-10-17","dataQuality":"complete","dataQualityNotes":"Name + EUR price verified on the retailer site on 2026-06-16. Re-check before production.","imageVerified":true},
  {"externalId":"ikea-hr-bathroom-storedamm-shelf-acacia","name":"STOREDAMM Regal, akacija, 60x141 cm","retailer":"IKEA","category":"storage","price":99.99,"productUrl":"https://www.ikea.com/hr/hr/p/storedamm-regal-akacija-10576167/","imageUrl":"https://www.ikea.com/hr/hr/images/products/storedamm-regal-akacija__1377209_pe960799_s5.jpg?f=xl","availabilityStatus":"in-stock","deliveryNote":"Provjeri dostavu ili preuzimanje prije kupnje.","lastCheckedAt":"2026-06-17","roomTags":["bathroom"],"styleTags":["cozy","classic"],"colorTags":["natural","brown"],"materialTags":["wood"],"priceTier":"budget","reviewRating":5,"reviewCount":7,"market":"HR","sourceType":"public-product-page","sourceName":"IKEA HR","sourceReference":"hr-bathroom-10-17","dataQuality":"complete","dataQualityNotes":"Name + EUR price verified on the retailer site on 2026-06-16. Re-check before production.","imageVerified":true},
  {"externalId":"ikea-hr-bathroom-muskan-shelf-white","name":"MUSKAN Regal, bijela, 37x140 cm","retailer":"IKEA","category":"storage","price":49.99,"productUrl":"https://www.ikea.com/hr/hr/p/muskan-regal-bijela-50424327/","imageUrl":"https://www.ikea.com/hr/hr/images/products/muskan-regal-bijela__0653131_pe707816_s5.jpg?f=xl","availabilityStatus":"in-stock","deliveryNote":"Provjeri dostavu ili preuzimanje prije kupnje.","lastCheckedAt":"2026-06-17","roomTags":["bathroom"],"styleTags":["minimal","modern"],"colorTags":["white"],"materialTags":["metal"],"priceTier":"budget","reviewRating":4.6,"reviewCount":402,"market":"HR","sourceType":"public-product-page","sourceName":"IKEA HR","sourceReference":"hr-bathroom-10-17","dataQuality":"complete","dataQualityNotes":"Name + EUR price verified on the retailer site on 2026-06-16. Re-check before production.","imageVerified":true},
  {"externalId":"ikea-hr-bathroom-ivoesjoen-cabinet-green","name":"IVÖSJÖN Element s vratima, zelena, 33x34x99 cm","retailer":"IKEA","category":"storage","price":24.99,"productUrl":"https://www.ikea.com/hr/hr/p/ivoesjoen-element-s-vratima-zelena-30569095/","imageUrl":"https://www.ikea.com/hr/hr/images/products/ivoesjoen-element-s-vratima-zelena__1383429_pe962557_s5.jpg?f=xl","availabilityStatus":"in-stock","deliveryNote":"Provjeri dostavu ili preuzimanje prije kupnje.","lastCheckedAt":"2026-06-17","roomTags":["bathroom"],"styleTags":["modern"],"colorTags":["green"],"materialTags":["metal"],"priceTier":"budget","reviewRating":4.2,"reviewCount":210,"market":"HR","sourceType":"public-product-page","sourceName":"IKEA HR","sourceReference":"hr-bathroom-10-17","dataQuality":"complete","dataQualityNotes":"Name + EUR price verified on the retailer site on 2026-06-16. Re-check before production.","imageVerified":true},
  {"externalId":"ikea-hr-bathroom-froesjoen-shelf-black","name":"FRÖSJÖN Regal, crna, 40x156 cm","retailer":"IKEA","category":"storage","price":49.99,"productUrl":"https://www.ikea.com/hr/hr/p/froesjoen-regal-crna-30574902/","imageUrl":"https://www.ikea.com/hr/hr/images/products/froesjoen-regal-crna__1253930_pe924359_s5.jpg?f=xl","availabilityStatus":"in-stock","deliveryNote":"Provjeri dostavu ili preuzimanje prije kupnje.","lastCheckedAt":"2026-06-17","roomTags":["bathroom"],"styleTags":["modern","industrial"],"colorTags":["black"],"materialTags":["metal"],"priceTier":"budget","reviewRating":4.8,"reviewCount":96,"market":"HR","sourceType":"public-product-page","sourceName":"IKEA HR","sourceReference":"hr-bathroom-10-17","dataQuality":"complete","dataQualityNotes":"Name + EUR price verified on the retailer site on 2026-06-16. Re-check before production.","imageVerified":true},
  {"externalId":"ikea-hr-bathroom-kabomba-ceiling-lamp-black","name":"KABOMBA LED stropna lampa, mat/crna, 36 cm","retailer":"IKEA","category":"lighting","price":59.99,"productUrl":"https://www.ikea.com/hr/hr/p/kabomba-led-stropna-lampa-mat-crna-60485278/","imageUrl":"https://www.ikea.com/hr/hr/images/products/kabomba-led-stropna-lampa-mat-crna__0990155_pe818782_s5.jpg?f=xl","availabilityStatus":"in-stock","deliveryNote":"Provjeri dostavu ili preuzimanje prije kupnje.","lastCheckedAt":"2026-06-17","roomTags":["bathroom"],"styleTags":["modern"],"colorTags":["black"],"materialTags":["metal"],"priceTier":"budget","reviewRating":3.7,"reviewCount":183,"market":"HR","sourceType":"public-product-page","sourceName":"IKEA HR","sourceReference":"hr-bathroom-10-17","dataQuality":"complete","dataQualityNotes":"Name + EUR price verified on the retailer site on 2026-06-16. Re-check before production.","imageVerified":true},
  {"externalId":"ikea-hr-bathroom-frihult-ceiling-lamp-black","name":"FRIHULT Stropna lampa, crna","retailer":"IKEA","category":"lighting","price":24.99,"productUrl":"https://www.ikea.com/hr/hr/p/frihult-stropna-lampa-crna-70431548/","imageUrl":"https://www.ikea.com/hr/hr/images/products/frihult-stropna-lampa-crna__0689511_pe723008_s5.jpg?f=xl","availabilityStatus":"in-stock","deliveryNote":"Provjeri dostavu ili preuzimanje prije kupnje.","lastCheckedAt":"2026-06-17","roomTags":["bathroom"],"styleTags":["industrial","modern"],"colorTags":["black"],"materialTags":["metal"],"priceTier":"budget","reviewRating":3.9,"reviewCount":62,"market":"HR","sourceType":"public-product-page","sourceName":"IKEA HR","sourceReference":"hr-bathroom-10-17","dataQuality":"complete","dataQualityNotes":"Name + EUR price verified on the retailer site on 2026-06-16. Re-check before production.","imageVerified":true},
  {"externalId":"ikea-hr-bathroom-ledsjoe-wall-lamp-steel","name":"LEDSJÖ LED zidna lampa, nehrđajući čelik","retailer":"IKEA","category":"lighting","price":49.99,"productUrl":"https://www.ikea.com/hr/hr/p/ledsjoe-led-zidna-lampa-nehrdajuci-celik-00529794/","imageUrl":"https://www.ikea.com/hr/hr/images/products/ledsjoe-led-zidna-lampa-nehrdajuci-celik__0582357_pe670678_s5.jpg?f=xl","availabilityStatus":"in-stock","deliveryNote":"Provjeri dostavu ili preuzimanje prije kupnje.","lastCheckedAt":"2026-06-17","roomTags":["bathroom"],"styleTags":["modern","minimal"],"colorTags":["grey"],"materialTags":["metal"],"priceTier":"budget","reviewRating":3.6,"reviewCount":70,"market":"HR","sourceType":"public-product-page","sourceName":"IKEA HR","sourceReference":"hr-bathroom-10-17","dataQuality":"complete","dataQualityNotes":"Name + EUR price verified on the retailer site on 2026-06-16. Re-check before production.","imageVerified":true},
  {"externalId":"ikea-hr-bathroom-barlast-lamp-white","name":"BARLAST LED stropna/zidna lampa, bijela, 25 cm","retailer":"IKEA","category":"lighting","price":5.99,"productUrl":"https://www.ikea.com/hr/hr/p/barlast-led-stropna-zidna-lampa-bijela-00525908/","imageUrl":"https://www.ikea.com/hr/hr/images/products/barlast-led-stropna-zidna-lampa-bijela__0772861_pe756185_s5.jpg?f=xl","availabilityStatus":"in-stock","deliveryNote":"Provjeri dostavu ili preuzimanje prije kupnje.","lastCheckedAt":"2026-06-17","roomTags":["bathroom"],"styleTags":["minimal"],"colorTags":["white"],"materialTags":["metal"],"priceTier":"budget","reviewRating":4.4,"reviewCount":673,"market":"HR","sourceType":"public-product-page","sourceName":"IKEA HR","sourceReference":"hr-bathroom-10-17","dataQuality":"complete","dataQualityNotes":"Name + EUR price verified on the retailer site on 2026-06-16. Re-check before production.","imageVerified":true},
  {"externalId":"ikea-hr-bathroom-lindbyn-mirror-black-50","name":"LINDBYN Ogledalo, crna, 50 cm","retailer":"IKEA","category":"decor","price":29.99,"productUrl":"https://www.ikea.com/hr/hr/p/lindbyn-ogledalo-crna-70590448/","imageUrl":"https://www.ikea.com/hr/hr/images/products/lindbyn-ogledalo-crna__1314762_pe940239_s5.jpg?f=xl","availabilityStatus":"in-stock","deliveryNote":"Provjeri dostavu ili preuzimanje prije kupnje.","lastCheckedAt":"2026-06-17","roomTags":["bathroom","hallway"],"styleTags":["modern","classic"],"colorTags":["black"],"materialTags":["metal"],"priceTier":"budget","reviewRating":4.7,"reviewCount":1464,"market":"HR","sourceType":"public-product-page","sourceName":"IKEA HR","sourceReference":"hr-bathroom-10-17","dataQuality":"complete","dataQualityNotes":"Name + EUR price verified on the retailer site on 2026-06-16. Re-check before production.","imageVerified":true},
  {"externalId":"ikea-hr-bathroom-nissedal-mirror-white-65","name":"NISSEDAL Ogledalo, bijela, 65x65 cm","retailer":"IKEA","category":"decor","price":24.99,"productUrl":"https://www.ikea.com/hr/hr/p/nissedal-ogledalo-bijela-20320312/","imageUrl":"https://www.ikea.com/hr/hr/images/products/nissedal-ogledalo-bijela__0637800_pe698596_s5.jpg?f=xl","availabilityStatus":"in-stock","deliveryNote":"Provjeri dostavu ili preuzimanje prije kupnje.","lastCheckedAt":"2026-06-17","roomTags":["bathroom","hallway"],"styleTags":["minimal","modern"],"colorTags":["white"],"materialTags":["wood"],"priceTier":"budget","reviewRating":4.7,"reviewCount":5601,"market":"HR","sourceType":"public-product-page","sourceName":"IKEA HR","sourceReference":"hr-bathroom-10-17","dataQuality":"complete","dataQualityNotes":"Name + EUR price verified on the retailer site on 2026-06-16. Re-check before production.","imageVerified":true}
]
